eQmaster/__init__.py
eQmaster/eQmaster.py
eQmaster/info.py
eQmaster/schema.py
eQmaster/features/__init__.py
eQmaster/features/bolinger_band.py
eQmaster/features/historical_volatility.py
eQmaster/features/market_beta.py
tests/__init__.py
tests/test_eqmaster.py
eQmaster-0.0.66.dist-info/LICENSE
eQmaster-0.0.66.dist-info/METADATA
eQmaster-0.0.66.dist-info/WHEEL
eQmaster-0.0.66.dist-info/top_level.txt
eQmaster-0.0.66.dist-info/RECORD
